ipart/AR_detector.py
ipart/AR_tracer.py
ipart/__init__.py
ipart/thr.py
ipart/utils/__init__.py
ipart/utils/funcs.py
ipart/utils/peak_prominence2d.py
ipart/utils/plot.py
ipart/utils/rdp.py
ipart-2.0.2.dist-info/LICENSE
ipart-2.0.2.dist-info/METADATA
ipart-2.0.2.dist-info/WHEEL
ipart-2.0.2.dist-info/top_level.txt
ipart-2.0.2.dist-info/RECORD
